portabellas/__init__.py
portabellas/containers/__init__.py
portabellas/containers/_cell/__init__.py
portabellas/containers/_cell/_cell.py
portabellas/containers/_cell/_expr_cell.py
portabellas/containers/_column.py
portabellas/containers/_row/__init__.py
portabellas/containers/_row/_expr_row.py
portabellas/containers/_row/_row.py
portabellas/containers/_table.py
portabellas/io/__init__.py
portabellas/io/_table_reader.py
portabellas/io/_table_writer.py
portabellas/plotting/__init__.py
portabellas/plotting/_column_plotter.py
portabellas/plotting/_table_plotter.py
portabellas/query/__init__.py
portabellas/query/_datetime_operations/__init__.py
portabellas/query/_datetime_operations/_datetime_operations.py
portabellas/query/_datetime_operations/_expr_datetime_operations.py
portabellas/query/_duration_operations/__init__.py
portabellas/query/_duration_operations/_duration_operations.py
portabellas/query/_duration_operations/_expr_duration_operations.py
portabellas/query/_math_operations/__init__.py
portabellas/query/_math_operations/_expr_math_operations.py
portabellas/query/_math_operations/_math_operations.py
portabellas/query/_string_operations/__init__.py
portabellas/query/_string_operations/_expr_string_operations.py
portabellas/query/_string_operations/_string_operations.py
portabellas/typing/__init__.py
portabellas/typing/_column_type.py
portabellas/typing/_schema.py
portabellas-0.2.0.dist-info/WHEEL
portabellas-0.2.0.dist-info/METADATA
portabellas-0.2.0.dist-info/RECORD
