Metadata-Version: 2.3
Name: portabellas
Version: 0.2.0
Summary: Add your description here
Requires-Dist: polars>=1.32.0
Requires-Python: >=3.12, <3.14
